<?xml version="1.0" encoding="utf-8"?>
<LanguageData>

  <ReviaFlechetteCannon.label>Флешеттное ружьё</ReviaFlechetteCannon.label>
  <ReviaFlechetteCannon.description>Крупнокалиберное ружьё, стреляющее дробовыми пулями. Очень опасно как вблизи, так и на дистанции, к тому же оснащено особым штыком.</ReviaFlechetteCannon.description>
  <ReviaFlechetteCannon.tools.0.label>приклад</ReviaFlechetteCannon.tools.0.label>
  <ReviaFlechetteCannon.tools.1.label>штык</ReviaFlechetteCannon.tools.1.label>

  <ReviaFlechetteCannonShard.label>осколок</ReviaFlechetteCannonShard.label>


</LanguageData>