<?xml version="1.0" encoding="utf-8" ?>
<Patch>
    <Operation Class="PatchOperationFindMod">
        <mods>
            <li>Vanilla Animals Expanded — Boreal Forest</li>
        </mods>
        <match Class="PatchOperationSequence">
            <operations>
                <li Class="PatchOperationAdd">
                    <xpath>/Defs/ThingDef[defName="AEXP_Otter"]/race/wildBiomes</xpath>
                    <value>
                        <AB_FeraliskInfestedJungle>0.01</AB_FeraliskInfestedJungle>
                        <AB_MycoticJungle>0.07</AB_MycoticJungle>
                        <AB_OcularForest>0.01</AB_OcularForest>
                        <AB_GelatinousSuperorganism>0.2</AB_GelatinousSuperorganism>
                    </value>
                </li>
                <li Class="PatchOperationAdd">
                    <xpath>/Defs/ThingDef[defName="AEXP_ArcticCoyote"]/race/wildBiomes</xpath>
                    <value>
                        <AB_PropaneLakes>0.07</AB_PropaneLakes>
                    </value>
                </li>
                <li Class="PatchOperationAdd">
                    <xpath>/Defs/ThingDef[defName="AEXP_BlackBear"]/race/wildBiomes</xpath>
                    <value>
                        <AB_MycoticJungle>0.01</AB_MycoticJungle>
                        <AB_OcularForest>0.07</AB_OcularForest>
                        <AB_GelatinousSuperorganism>0.01</AB_GelatinousSuperorganism>
                    </value>
                </li>
            </operations>
        </match>
    </Operation>
</Patch>