<?xml version="1.0" encoding="utf-8"?>
<LanguageData>

                <AA_Nightling.label>найтлинг</AA_Nightling.label>
                <AA_Nightling.labelPlural>найтлинги</AA_Nightling.labelPlural>
		<AA_Nightling.lifeStages.0.label>щенок найтлинга</AA_Nightling.lifeStages.0.label>
		<AA_Nightling.lifeStages.0.labelPlural>щенята найтлинга</AA_Nightling.lifeStages.0.labelPlural>
		<AA_Nightling.lifeStages.1.label>молодой найтлинг</AA_Nightling.lifeStages.1.label>
		<AA_Nightling.lifeStages.1.labelPlural>молодые найтлинги</AA_Nightling.lifeStages.1.labelPlural>
</LanguageData>








































