<?xml version="1.0" encoding="utf-8"?>
<LanguageData>

                <AA_RayHound.label>электрогончая</AA_RayHound.label>
                <AA_RayHound.labelPlural>электрогончие</AA_RayHound.labelPlural>
		<AA_RayHound.lifeStages.0.label>детёныш электрогончей</AA_RayHound.lifeStages.0.label>
		<AA_RayHound.lifeStages.0.labelPlural>детёныши электрогончей</AA_RayHound.lifeStages.0.labelPlural>
		<AA_RayHound.lifeStages.1.label>молодая электрогончая</AA_RayHound.lifeStages.1.label>
		<AA_RayHound.lifeStages.1.labelPlural>молодые электрогончие</AA_RayHound.lifeStages.1.labelPlural>

</LanguageData>


















