<?xml version="1.0" encoding="utf-8" ?>
<Defs>

  <BodyPartDef>
    <defName>Crest</defName>
    <label>crest</label>
    <hitPoints>20</hitPoints>
    <permanentInjuryChanceFactor>0</permanentInjuryChanceFactor>
    <skinCovered>true</skinCovered>
  </BodyPartDef>

  <BodyPartDef>
    <defName>Spikes</defName>
    <label>spikes</label>
    <hitPoints>20</hitPoints>
    <frostbiteVulnerability>0</frostbiteVulnerability>
    <permanentInjuryChanceFactor>0</permanentInjuryChanceFactor>
    <skinCovered>false</skinCovered>
  </BodyPartDef>
  
  <BodyPartDef>
    <defName>Club</defName>
    <label>club</label>
    <hitPoints>20</hitPoints>
    <frostbiteVulnerability>0</frostbiteVulnerability>
    <permanentInjuryChanceFactor>0.00</permanentInjuryChanceFactor>
    <skinCovered>false</skinCovered>
  </BodyPartDef>
  
  <BodyPartDef>
    <defName>SkullDome</defName>
    <label>skull dome</label>
    <hitPoints>20</hitPoints>
    <frostbiteVulnerability>0</frostbiteVulnerability>
    <permanentInjuryChanceFactor>0.00</permanentInjuryChanceFactor>
    <skinCovered>false</skinCovered>
  </BodyPartDef>
  
  <BodyPartDef ParentName="ClawBase">
    <defName>FootClaw</defName>
    <label>sickle claw</label>
    <labelShort>claw</labelShort>
    <tags>
      <li>MovingLimbDigit</li>
    </tags>
  </BodyPartDef>
  
  <BodyPartDef>
    <defName>Knucklehead</defName>
    <label>knucklehead</label>
    <hitPoints>30</hitPoints>
    <frostbiteVulnerability>0</frostbiteVulnerability>
    <permanentInjuryChanceFactor>15</permanentInjuryChanceFactor>
    <skinCovered>false</skinCovered>
  </BodyPartDef>

</Defs>