<?xml version="1.0" encoding="utf-8" ?>
<Defs>

    <TerrainDef ParentName="NaturalTerrainBase">
        <defName>AB_ForsakenSand</defName>
        <label>forsaken sand</label>
        <texturePath>Terrain/Surfaces/AB_ForsakenSands</texturePath>
        <edgeType>FadeRough</edgeType>
        <renderPrecedence>340</renderPrecedence>
        <pathCost>4</pathCost>
        <statBases>
            <Beauty>-3</Beauty>
            <BeautyOutdoors>0</BeautyOutdoors>
            <Cleanliness>-1</Cleanliness>
        </statBases>
        <scatterType>AB_DarkScatter</scatterType>
        <affordances>
            <li>Light</li>
            <li>Medium</li>
            <li>Heavy</li>
            <li>GrowSoil</li>
            <li>Diggable</li>
        </affordances>
        <generatedFilth>Filth_Dirt</generatedFilth>
        <fertility>1.0</fertility>
        <takeFootprints>True</takeFootprints>
        <tools>
            <li>
                <label>dirt</label>
                <capacities>
                    <li>KickMaterialInEyes</li>
                </capacities>
                <hediff>DirtInEyes</hediff>
                <cooldownTime>1.5</cooldownTime>
            </li>
        </tools>
        <tags>
            <li>Soil</li>
			<li>Sand</li>
		</tags>
    </TerrainDef>
  
    <TerrainDef ParentName="NaturalTerrainBase">
        <defName>AB_FineForsakenSand</defName>
        <label>fine forsaken sand</label>
        <texturePath>Terrain/Surfaces/AB_FineForsakenSands</texturePath>
        <edgeType>FadeRough</edgeType>
        <renderPrecedence>350</renderPrecedence>
        <pathCost>4</pathCost>
        <statBases>
            <Beauty>-3</Beauty>
            <BeautyOutdoors>0</BeautyOutdoors>
            <Cleanliness>-1</Cleanliness>
        </statBases>
        <scatterType>AB_DarkScatter</scatterType>
        <affordances>
            <li>Light</li>
            <li>Medium</li>
            <li>Heavy</li>
            <li>Diggable</li>
        </affordances>
        <generatedFilth>Filth_Sand</generatedFilth>
        <fertility>0.10</fertility>
        <takeFootprints>True</takeFootprints>
        <tools>
            <li>
                <label>sand</label>
                <capacities>
                    <li>KickMaterialInEyes</li>
                </capacities>
                <hediff>SandInEyes</hediff>
                <cooldownTime>1.5</cooldownTime>
            </li>
        </tools>
        <tags>
            <li>Soil</li>
			<li>Sand</li>
		</tags>
    </TerrainDef>
  
    <TerrainDef ParentName="NaturalTerrainBase">
        <defName>AB_ForsakenRock</defName>
        <label>forsaken rocks</label>
        <texturePath>Terrain/Surfaces/AB_ForsakenRocks</texturePath>
        <edgeType>FadeRough</edgeType>
        <renderPrecedence>320</renderPrecedence>
        <pathCost>10</pathCost>
        <statBases>
            <Beauty>-3</Beauty>
            <BeautyOutdoors>0</BeautyOutdoors>
            <Cleanliness>-1</Cleanliness>
        </statBases>
        <scatterType>AB_DarkScatter</scatterType>
        <affordances>
            <li>Light</li>
            <li>Medium</li>
            <li>Heavy</li>
            <li>GrowSoil</li>
            <li>Diggable</li>
        </affordances>
        <generatedFilth>Filth_Dirt</generatedFilth>
        <fertility>0.7</fertility>
        <takeFootprints>True</takeFootprints>
        <tools>
            <li>
                <label>gravel</label>
                <capacities>
                    <li>KickMaterialInEyes</li>
                </capacities>
                <hediff>GravelInEyes</hediff>
                <cooldownTime>1.5</cooldownTime>
            </li>
        </tools>
        <tags>
            <li>Soil</li>
		</tags>
    </TerrainDef>
  
    <TerrainDef ParentName="NaturalTerrainBase">
        <defName>AB_DarkMud</defName>
        <label>forsaken mud</label>
        <texturePath>Terrain/Surfaces/AB_DarkMud</texturePath>
        <edgeType>FadeRough</edgeType>
        <renderPrecedence>330</renderPrecedence>
        <pathCost>12</pathCost>
        <statBases>
            <Beauty>-3</Beauty>
            <BeautyOutdoors>0</BeautyOutdoors>
            <Cleanliness>-2</Cleanliness>
        </statBases>
        <affordances>
			<li>Light</li>
			<li>Diggable</li>
			<li>Bridgeable</li>
            <li>AB_TarAffordance</li>
		</affordances>
        <generatedFilth>Filth_Dirt</generatedFilth>
        <fertility>0</fertility>
        <takeFootprints>True</takeFootprints>
        <avoidWander>true</avoidWander>
        <driesTo>Soil</driesTo>
        <tools>
            <li>
                <label>mud</label>
                <capacities>
                    <li>KickMaterialInEyes</li>
                </capacities>
                <hediff>MudInEyes</hediff>
                <cooldownTime>1.5</cooldownTime>
            </li>
        </tools>
    </TerrainDef>
</Defs>