<?xml version="1.0" encoding="utf-8"?>
<LanguageData>

<AA_OcularJellyBody.label>окулярная медуза</AA_OcularJellyBody.label>
<AA_OcularJellyBody.corePart.parts.0.customLabel>желудочный мешок</AA_OcularJellyBody.corePart.parts.0.customLabel>
<AA_OcularJellyBody.corePart.parts.1.customLabel>гастроваскулярная полость</AA_OcularJellyBody.corePart.parts.1.customLabel>
<AA_OcularJellyBody.corePart.parts.2.customLabel>левый водородный мешок</AA_OcularJellyBody.corePart.parts.2.customLabel>
<AA_OcularJellyBody.corePart.parts.3.customLabel>правый водородный мешок</AA_OcularJellyBody.corePart.parts.3.customLabel>
<AA_OcularJellyBody.corePart.parts.4.parts.0.customLabel>первый глаз</AA_OcularJellyBody.corePart.parts.4.parts.0.customLabel>
<AA_OcularJellyBody.corePart.parts.4.parts.1.customLabel>второй глаз</AA_OcularJellyBody.corePart.parts.4.parts.1.customLabel>
<AA_OcularJellyBody.corePart.parts.4.parts.2.customLabel>третий глаз</AA_OcularJellyBody.corePart.parts.4.parts.2.customLabel>
<AA_OcularJellyBody.corePart.parts.4.parts.3.customLabel>четвертый глаз</AA_OcularJellyBody.corePart.parts.4.parts.3.customLabel>
<AA_OcularJellyBody.corePart.parts.4.parts.4.customLabel>пятый глаз</AA_OcularJellyBody.corePart.parts.4.parts.4.customLabel>
<AA_OcularJellyBody.corePart.parts.5.customLabel>первое щупальце</AA_OcularJellyBody.corePart.parts.5.customLabel>
<AA_OcularJellyBody.corePart.parts.6.customLabel>второе щупальце</AA_OcularJellyBody.corePart.parts.6.customLabel>
<AA_OcularJellyBody.corePart.parts.7.customLabel>третье щупальце</AA_OcularJellyBody.corePart.parts.7.customLabel>


</LanguageData>

