<?xml version="1.0" encoding="utf-8"?>
<LanguageData>

 <Ceratopsid.label>цератопсид</Ceratopsid.label>
  <Ceratopsid.corePart.parts.4.customLabel>левое легкое</Ceratopsid.corePart.parts.4.customLabel>
  <Ceratopsid.corePart.parts.5.customLabel>правое легкое</Ceratopsid.corePart.parts.5.customLabel>
  <Ceratopsid.corePart.parts.6.customLabel>левая почка</Ceratopsid.corePart.parts.6.customLabel>
  <Ceratopsid.corePart.parts.7.customLabel>правая почка</Ceratopsid.corePart.parts.7.customLabel>
  <Ceratopsid.corePart.parts.9.parts.0.parts.2.customLabel>левый глаз</Ceratopsid.corePart.parts.9.parts.0.parts.2.customLabel>
  <Ceratopsid.corePart.parts.9.parts.0.parts.3.customLabel>правый глаз</Ceratopsid.corePart.parts.9.parts.0.parts.3.customLabel>
  <Ceratopsid.corePart.parts.9.parts.0.parts.6.customLabel>левый рог</Ceratopsid.corePart.parts.9.parts.0.parts.6.customLabel>
  <Ceratopsid.corePart.parts.9.parts.0.parts.7.customLabel>правый рог</Ceratopsid.corePart.parts.9.parts.0.parts.7.customLabel>
  <Ceratopsid.corePart.parts.9.parts.0.parts.8.customLabel>передний рупор</Ceratopsid.corePart.parts.9.parts.0.parts.8.customLabel>
  <Ceratopsid.corePart.parts.10.customLabel>левая передняя нога</Ceratopsid.corePart.parts.10.customLabel>
  <Ceratopsid.corePart.parts.10.parts.0.customLabel>передняя левая нога</Ceratopsid.corePart.parts.10.parts.0.customLabel>
  <Ceratopsid.corePart.parts.11.customLabel>передняя правая нога</Ceratopsid.corePart.parts.11.customLabel>
  <Ceratopsid.corePart.parts.11.parts.0.customLabel>передняя правая нога</Ceratopsid.corePart.parts.11.parts.0.customLabel>
  <Ceratopsid.corePart.parts.12.customLabel>задняя левая нога</Ceratopsid.corePart.parts.12.customLabel>
  <Ceratopsid.corePart.parts.12.parts.0.customLabel>задняя левая нога</Ceratopsid.corePart.parts.12.parts.0.customLabel>
  <Ceratopsid.corePart.parts.13.customLabel>правая задняя нога</Ceratopsid.corePart.parts.13.customLabel>
  <Ceratopsid.corePart.parts.13.parts.0.customLabel>задняя правая нога</Ceratopsid.corePart.parts.13.parts.0.customLabel>


</LanguageData>